zinc/__init__.py
zinc/codegen.py
zinc/codegen_cli.py
zinc/openapi_conversion.py
zinc/api/__init__.py
zinc/api/codegen_api.py
zinc/openapi_schema_pydantic/__init__.py
zinc/openapi_schema_pydantic/components.py
zinc/openapi_schema_pydantic/contact.py
zinc/openapi_schema_pydantic/discriminator.py
zinc/openapi_schema_pydantic/example.py
zinc/openapi_schema_pydantic/external_documentation.py
zinc/openapi_schema_pydantic/info.py
zinc/openapi_schema_pydantic/license.py
zinc/openapi_schema_pydantic/link.py
zinc/openapi_schema_pydantic/media_type.py
zinc/openapi_schema_pydantic/oauth_flow.py
zinc/openapi_schema_pydantic/oauth_flows.py
zinc/openapi_schema_pydantic/open_api.py
zinc/openapi_schema_pydantic/operation.py
zinc/openapi_schema_pydantic/parameter.py
zinc/openapi_schema_pydantic/path_item.py
zinc/openapi_schema_pydantic/paths.py
zinc/openapi_schema_pydantic/reference.py
zinc/openapi_schema_pydantic/request_body.py
zinc/openapi_schema_pydantic/response.py
zinc/openapi_schema_pydantic/responses.py
zinc/openapi_schema_pydantic/schema.py
zinc/openapi_schema_pydantic/security_requirement.py
zinc/openapi_schema_pydantic/security_scheme.py
zinc/openapi_schema_pydantic/server.py
zinc/openapi_schema_pydantic/server_variable.py
zinc/openapi_schema_pydantic/tag.py
zinc/openapi_schema_pydantic/xml.py
zinc_api-0.0.3.dist-info/METADATA
zinc_api-0.0.3.dist-info/WHEEL
zinc_api-0.0.3.dist-info/entry_points.txt
zinc_api-0.0.3.dist-info/namespace_packages.txt
zinc_api-0.0.3.dist-info/top_level.txt
zinc_api-0.0.3.dist-info/RECORD
