Metadata-Version: 2.1
Name: zinc-api
Version: 0.0.3
Summary: UNKNOWN
Home-page: UNKNOWN
License: UNKNOWN
Platform: UNKNOWN
Requires-Dist: black (~=22.1.0)
Requires-Dist: click (~=8.0.3)
Requires-Dist: inflection (~=0.5.1)
Requires-Dist: isort (~=5.10.1)
Requires-Dist: pydantic (~=1.9.0)
Requires-Dist: pyyaml (~=6.0)
Requires-Dist: types-pyyaml (~=6.0.3)
